Metadata-Version: 2.1
Name: neuroedge-sdk2
Version: 1.1.0
Summary: This module enables logging of parameters, metrics, and artifacts to MLflow using the Tracking Log Model SDK. It also provides functionality to persist models to Amazon S3 based on specific message types.
Author: Saurav Kumar
Author-email: Saurav.Kumar@cognizant.com
Classifier: Programming Language :: Python :: 3
Classifier: License :: OSI Approved :: MIT License
Classifier: Operating System :: OS Independent
Requires-Python: >=3.6
License-File: LICENSE.lic
